assignment1/problem1/problem1.sv
// problem1.sv - for Assignmetn 1: designign a priority encoder
// Teylor Wong 01-29-225

module encoder (
    output logic [1:0] y,
    output logic valid,
    input logic [3:0] a );

    always_comb begin
        casex(a)
        4'b1xxx: begin y = 2'b11; valid = 1'b1; end
        4'b01xx: begin y = 2'b10; valid = 1'b1; end
        4'b001x: begin y = 2'b01; valid = 1'b1; end
        4'b0001: begin y = 2'b00; valid = 1'b1; end
        4'b0000: begin y = 2'b00; valid = 1'b0; end
        endcase
    end

endmodule

assignment1/problem1/problem1_tb.sv
// problem1_tb.sv - for Assignmetn 1: Testbench for the priority encoder
// Teylor Wong 01-29-225

module encoder_tb ();
    // Test signals
    logic [3:0] a;
    logic [1:0] y;
    logic valid;

    // Instantiate the encoder
    encoder dut(.y(y), .valid(valid), .a(a));
    
    // Test stimulus
    initial begin
        $display("Starting test");

        // Test 16 combinations (0000 to 1111)
        for (int i = 0; i < 16, i++) begin
            a = 1;
            #10;
            $display("Input a=%4b, Output y=%2b, valid=%b", a, y, valid);
        end

        $finish;
    end

    // Create waveform
    initial begin
        $dumpfile("encoder_wave.vcd");  // Create wave file
        $dumpvars(0, encoder_tb);       // Dump variables
    end

endmodule

assignment1/problem1/Simulation/encoder_wave.vcd
$date
	Wed Jan 29 13:28:12 2025
$end
$version
	ModelSim Version 10.5b
$end
$timescale
	1ps
$end

$scope module encoder_tb $end
$var reg 4 ! a [3:0] $end
$var reg 2 " y [1:0] $end
$var reg 1 # valid $end

$scope module dut $end
$var wire 1 $ a [3] $end
$var wire 1 % a [2] $end
$var wire 1 & a [1] $end
$var wire 1 ' a [0] $end
$var reg 2 ( y [1:0] $end
$var reg 1 ) valid $end
$upscope $end
$upscope $end
$enddefinitions $end
#0
$dumpvars
b0 !
b0 "
0#
b0 (
0)
0'
0&
0%
0$
$end
#10
b1 !
1'
1)
1#
#20
b10 !
0'
1&
b1 (
b1 "
#30
b11 !
1'
#40
b100 !
0'
0&
1%
b10 (
b10 "
#50
b101 !
1'
#60
b110 !
0'
1&
#70
b111 !
1'
#80
b1000 !
0'
0&
0%
1$
b11 (
b11 "
#90
b1001 !
1'
#100
b1010 !
0'
1&
#110
b1011 !
1'
#120
b1100 !
0'
0&
1%
#130
b1101 !
1'
#140
b1110 !
0'
1&
#150
b1111 !
1'
