assignment2/problem1/Modules/seqDetect.sv
// Assignment 2: Problem1 - Sequence Detector
// seqDetect.sv - valid is asserted for one clock cycle if last N 'a' bits match the sequence
// Teylor Wong 12-02-2025

module seqDetect #(parameter N=6) (
    output logic valid,
    input logic a, input logic [N-1:0] seq,
    input logic clk, reset_n );

    logic [N-1:0] reg_seq; // register to store the sequence
    int bit_counter;  // tracks # of bits input

always_ff @(posedge clk or negedge reset_n) begin
    if (~reset_n) begin
        reg_seq <= 0;
        valid <= 0;
        bit_counter <= 0;
    end
    else begin
        if (bit_counter < N) 
            bit_counter <= bit_counter + 1;

        if (bit_counter >= N-1) begin
            if (reg_seq == seq) 
                valid <= 1;
            else 
                valid <= 0;
        end
        
        reg_seq <= {reg_seq[N-2:0], a}; // Now shift AFTER checking
    end
end

endmodule

assignment2/problem1/Simulation/seqDetect_tb.sv
// Assignment 2: Problem1 - Sequence Detector Testbench
// seqDetect_tb.sv - tests module as a 3-bit sequence detector (N=3)
// Teylor Wong 12-02-2025

module seqDetect_tb;

    logic valid, a;  
    logic [2:0] seq;
    logic clk, reset_n;

    seqDetect #(.N(3)) dut(.valid(valid), .a(a), .seq(seq), .clk(clk), .reset_n(reset_n));

    // clock that toggles every 5 time units
    always begin
        clk = 0; #5;
        clk = 1; #5;
    end

    // Testing
    initial begin
        // Initialize signals
        reset_n = 0;
        a = 0;
        seq = 3'b110; // Set a specific sequence
        $display("Sequence to detect: %b", seq);
        #10;

        reset_n = 1;
        #10;

        // Test all 3-bit combinations
        a = 0; #10; a = 0; #10; a = 0; #10; #10;
        $display("Input: 000, Valid: %b", valid);

        a = 0; #10; a = 0; #10; a = 1; #10; #10;
        $display("Input: 001, Valid: %b", valid);

        a = 0; #10; a = 1; #10; a = 0; #10; #10;
        $display("Input: 010, Valid: %b", valid);

        a = 0; #10; a = 1; #10; a = 1; #10; #10;
        $display("Input: 011, Valid: %b", valid);

        a = 1; #10; a = 0; #10; a = 0; #10; #10;
        $display("Input: 100, Valid: %b", valid);

        a = 1; #10; a = 0; #10; a = 1; #10; #10;
        $display("Input: 101, Valid: %b", valid);

        a = 1; #10; a = 1; #10; a = 0; #10; #10;
        $display("Input: 110, Valid: %b", valid);

        a = 1; #10; a = 1; #10; a = 1; #10; #10;
        $display("Input: 111, Valid: %b", valid);

        $stop;
    end

    initial begin
        $dumpfile("seqDetect_wave.vcd");
        $dumpvars(0, seqDetect_tb);
    end
endmodule

assignment2/problem1/Simulation/seqDetect_wave.vcd
$date
	Thu Feb 13 14:34:55 2025
$end
$version
	ModelSim Version 10.5b
$end
$timescale
	1ps
$end

$scope module seqDetect_tb $end
$var reg 1 ! valid $end
$var reg 1 " a $end
$var reg 3 # seq [2:0] $end
$var reg 1 $ clk $end
$var reg 1 % reset_n $end

$scope module dut $end
$var parameter 32 & N $end
$var reg 1 ' valid $end
$var wire 1 ( a $end
$var wire 1 ) seq [2] $end
$var wire 1 * seq [1] $end
$var wire 1 + seq [0] $end
$var wire 1 , clk $end
$var wire 1 - reset_n $end
$var reg 3 . reg_seq [2:0] $end
$var integer 32 / bit_counter $end
$upscope $end
$upscope $end
$enddefinitions $end
#0
$dumpvars
0!
0"
b110 #
0$
0%
0'
b0 .
b11 &
b0 /
0(
0+
1*
1)
0,
0-
$end
#5
1$
1,
#10
1%
0$
1-
0,
#15
1$
1,
b1 /
#20
0$
0,
#25
1$
1,
b10 /
#30
0$
0,
#35
1$
1,
b11 /
#40
0$
0,
#45
1$
1,
#50
0$
0,
#55
1$
1,
#60
0$
0,
#65
1$
1,
#70
0$
0,
#75
1$
1,
#80
1"
0$
1(
0,
#85
1$
1,
b1 .
#90
0$
0,
#95
1$
1,
b11 .
#100
0"
0$
0(
0,
#105
1$
1,
b110 .
#110
1"
0$
1(
0,
#115
1$
1,
1'
b101 .
1!
#120
0"
0$
0(
0,
#125
1$
1,
0'
b10 .
0!
#130
0$
0,
#135
1$
1,
b100 .
#140
0$
0,
#145
1$
1,
b0 .
#150
1"
0$
1(
0,
#155
1$
1,
b1 .
#160
0$
0,
#165
1$
1,
b11 .
#170
0$
0,
#175
1$
1,
b111 .
#180
0$
0,
#185
1$
1,
#190
0"
0$
0(
0,
#195
1$
1,
b110 .
#200
0$
0,
#205
1$
1,
1'
b100 .
1!
#210
0$
0,
#215
1$
1,
0'
b0 .
0!
#220
1"
0$
1(
0,
#225
1$
1,
b1 .
#230
0"
0$
0(
0,
#235
1$
1,
b10 .
#240
1"
0$
1(
0,
#245
1$
1,
b101 .
#250
0$
0,
#255
1$
1,
b11 .
#260
0$
0,
#265
1$
1,
b111 .
#270
0$
0,
#275
1$
1,
#280
0"
0$
0(
0,
#285
1$
1,
b110 .
#290
0$
0,
#295
1$
1,
1'
b100 .
1!
#300
1"
0$
1(
0,
#305
1$
1,
0'
b1 .
0!
#310
0$
0,
#315
1$
1,
b11 .
#320
0$
0,
#325
1$
1,
b111 .
