assignment2/problem1/Modules/seqDetect.sv
// Assignment 2: Problem1 - Sequence Detector
// seqDetect.sv - valid is asserted for one clock cycle if last N 'a' bits match the sequence
// Teylor Wong 12-02-2025

module seqDetect #(parameter N=6) (
    output logic valid,
    input logic a, input logic [N-1:0] seq,
    input logic clk, reset_n );

    logic [N-1:0] reg_seq; // register to store the sequence
    int bit_counter;  // tracks # of bits input

always_ff @(posedge clk or negedge reset_n) begin
    if (~reset_n) begin
        reg_seq <= 0;
        valid <= 0;
        bit_counter <= 0;
    end
    else begin
        if (bit_counter < N) 
            bit_counter <= bit_counter + 1;

        if (bit_counter >= N-1) begin
            if (reg_seq == seq) 
                valid <= 1;
            else 
                valid <= 0;
        end
        
        reg_seq <= {reg_seq[N-2:0], a}; // Now shift AFTER checking
    end
end

endmodule

problem1/Simulation/seqDetect_tb.sv
// Assignment 2: Problem1 - Sequence Detector Testbench
// seqDetect_tb.sv - tests module as a 3-bit sequence detector (N=3)
// Teylor Wong 12-02-2025

module seqDetect_tb;

    logic valid, a;  
    logic [2:0] seq;
    logic clk, reset_n;

    seqDetect dut(.valid(valid), .a(a), .seq(seq), .clk(clk), .reset_n(reset_n));

    // clock that toggles every 5 time units
    always begin
        clk = 0; #5;
        clk = 1; #5;
    end

    // Testing
    initial begin
        // Initialize signals
        reset_n = 0;
        a = 0;
        // set a random 3 bit value to seq (from ChatGPT)
        $random(42);
        seq = $random % 8;  // between 0 and 7
        $display("Random sequence to detect: %b", seq);
        #10;    // Wait a bit

        reset_n = 1;
        #10;

        // Test all 3-bit combinations
        // Test 000
        a = 0; #10; a = 0; #10; a = 0; #10;
        $display("Input: 000, Valid: %b", valid);

        // Test 001
        a = 0; #10; a = 0; #10; a = 1; #10;
        $display("Input: 001, Valid: %b", valid);

        // Test 010
        a = 0; #10; a = 1; #10; a = 0; #10;
        $display("Input: 010, Valid: %b", valid);

        // Test 011
        a = 0; #10; a = 1; #10; a = 1; #10;
        $display("Input: 011, Valid: %b", valid);

        // Test 100
        a = 1; #10; a = 0; #10; a = 0; #10;
        $display("Input: 100, Valid: %b", valid);

        // Test 101
        a = 1; #10; a = 0; #10; a = 1; #10;
        $display("Input: 101, Valid: %b", valid);

        // Test 110
        a = 1; #10; a = 1; #10; a = 0; #10;
        $display("Input: 110, Valid: %b", valid);

        // Test 111
        a = 1; #10; a = 1; #10; a = 1; #10;
        $display("Input: 111, Valid: %b", valid);

        $stop;
    end

    initial begin
        $dumpfile("shiftreg_wave.vcd");
        $dumpvars(0, seqDetect_tb);
    end


endmodule

assignment2/problem1/Simulation/shiftreg_wave.vcd
$date
	Thu Feb 13 12:54:53 2025
$end
$version
	ModelSim Version 10.5b
$end
$timescale
	1ps
$end

$scope module seqDetect_tb $end
$var reg 1 ! valid $end
$var reg 1 " a $end
$var reg 3 # seq [2:0] $end
$var reg 1 $ clk $end
$var reg 1 % reset_n $end

$scope module dut $end
$var parameter 32 & N $end
$var reg 1 ' valid $end
$var wire 1 ( a $end
$var wire 1 ) seq [5] $end
$var wire 1 * seq [4] $end
$var wire 1 + seq [3] $end
$var wire 1 , seq [2] $end
$var wire 1 - seq [1] $end
$var wire 1 . seq [0] $end
$var wire 1 / clk $end
$var wire 1 0 reset_n $end
$var reg 6 1 reg_seq [5:0] $end
$var reg 6 2 bit_counter [5:0] $end
$upscope $end
$upscope $end
$enddefinitions $end
#0
$dumpvars
0!
0"
b101 #
0$
0%
0'
b0 1
b0 2
b110 &
0(
1.
0-
1,
0/
00
z+
z*
z)
$end
#5
1$
1/
#10
1%
0$
10
0/
#15
1$
1/
b1 2
#20
0$
0/
#25
1$
1/
b10 2
#30
0$
0/
#35
1$
1/
b11 2
#40
0$
0/
#45
1$
1/
b100 2
#50
0$
0/
#55
1$
1/
b101 2
#60
0$
0/
#65
1$
1/
b110 2
#70
1"
0$
1(
0/
#75
1$
1/
b1 1
#80
0"
0$
0(
0/
#85
1$
1/
b10 1
#90
1"
0$
1(
0/
#95
1$
1/
b101 1
#100
0"
0$
0(
0/
#105
1$
1/
b1010 1
#110
0$
0/
#115
1$
1/
b10100 1
#120
1"
0$
1(
0/
#125
1$
1/
b101001 1
#130
0$
0/
#135
1$
1/
b10011 1
#140
0$
0/
#145
1$
1/
b100111 1
#150
0"
0$
0(
0/
#155
1$
1/
b1110 1
#160
0$
0/
#165
1$
1/
b11100 1
#170
1"
0$
1(
0/
#175
1$
1/
b111001 1
#180
0"
0$
0(
0/
#185
1$
1/
b110010 1
#190
1"
0$
1(
0/
#195
1$
1/
b100101 1
#200
0$
0/
#205
1$
1/
b1011 1
#210
0$
0/
#215
1$
1/
b10111 1
#220
0"
0$
0(
0/
#225
1$
1/
b101110 1
#230
1"
0$
1(
0/
#235
1$
1/
b11101 1
#240
0$
0/
#245
1$
1/
b111011 1
#250
0$
0/
#255
1$
1/
b110111 1
