assignment1/problem2/Modules/problem2.sv
// problem2.sv - for Assignment 1: Designing an 8-bit shift register with
// an asynchronous active low reset and functionality from given table
// Teylor Wong 01-29-25

module problem2 (
    input logic [7:0] a,
    input logic [1:0] s,
    input logic shiftIn, clk, reset_n,
    output logic [7:0] q );

    always_ff @(posedge clk or negedge reset_n) begin
        if (!reset_n) begin
            q <= 8'b0;  // reset to zeros
        end
        else begin
            case(s)
                2'b00: q <= a;                  // Parallel load
                2'b01: q <= {shiftIn, a[7:1]};  // Shift right
                2'b10: q <= {a[6:0], shiftIn};  // Shift left
                2'b11: q <= q;                  // Hold
            endcase
        end
    end
endmodule

assignment1/problem2/Simulations/problem2_tb.sv
// problem2_tb.sv - for Assignment 1: Tetbench simulation for the 8-bit shift register
// Teylor Wong 01-29-25

module problem2_tb();
    logic [7:0] q;        // output
    logic [7:0] a;        // input
    logic [1:0] s;        // input
    logic shiftIn;        // input
    logic clk, reset_n;

    problem2 dut(.q(q), .a(a), .s(s), .shiftIn(shiftIn), .clk(clk), .reset_n(reset_n));

    // clock that toggles every 5 time units
    always begin
        clk = 0; #5;
        clk = 1; #5;
    end

    // Testing
    initial begin
        // Initialize signals
        reset_n = 0;
        a = 8'b10101010;  // Test data
        s = 2'b00;
        shiftIn = 0;
        #10;

        reset_n = 1;
        #10;

        // Test parallel load (s = 00)
        $display("Testing parallel load");
        #10;
        // Test shift right (s = 01)
        s = 2'b01;
        shiftIn = 1;
        $display("Testing shift right");
        #20;
        // Test shift left (s = 10)
        s = 2'b10;
        shiftIn = 0;
        $display("Testing shift left");
        #20;
        // Test hold (s = 11)
        s = 2'b11;
        $display("Testing hold");
        #20;

        $stop;
    end

    // Create waveform - by ChatGPT
    initial begin
        $dumpfile("shiftreg_wave.vcd");
        $dumpvars(0, problem2_tb);
    end

endmodule

assignment1/problem2/Simulations/shiftreg_wave.vcd
$date
	Sat Feb 01 10:47:10 2025
$end
$version
	ModelSim Version 10.5b
$end
$timescale
	1ps
$end

$scope module problem2_tb $end
$var reg 8 ! q [7:0] $end
$var reg 8 " a [7:0] $end
$var reg 2 # s [1:0] $end
$var reg 1 $ shiftIn $end
$var reg 1 % clk $end
$var reg 1 & reset_n $end

$scope module dut $end
$var wire 1 ' a [7] $end
$var wire 1 ( a [6] $end
$var wire 1 ) a [5] $end
$var wire 1 * a [4] $end
$var wire 1 + a [3] $end
$var wire 1 , a [2] $end
$var wire 1 - a [1] $end
$var wire 1 . a [0] $end
$var wire 1 / s [1] $end
$var wire 1 0 s [0] $end
$var wire 1 1 shiftIn $end
$var wire 1 2 clk $end
$var wire 1 3 reset_n $end
$var reg 8 4 q [7:0] $end
$upscope $end
$upscope $end
$enddefinitions $end
#0
$dumpvars
b0 !
b10101010 "
b0 #
0$
0%
0&
b0 4
0.
1-
0,
1+
0*
1)
0(
1'
00
0/
01
02
03
$end
#5
1%
12
#10
1&
0%
13
02
#15
1%
12
b10101010 4
b10101010 !
#20
0%
02
#25
1%
12
#30
b1 #
1$
0%
10
11
02
#35
1%
12
b11010101 4
b11010101 !
#40
0%
02
#45
1%
12
#50
b10 #
0$
0%
00
1/
01
02
#55
1%
12
b1010100 4
b1010100 !
#60
0%
02
#65
1%
12
#70
b11 #
0%
10
02
