assignment2/problem2/Modules/vendingMachine.sv
// Assignment 2: Problem2 - Vending Machine
// vendingMachine.sv - keeps track of the amount of money put
// into a vending machine and asserts the valid output for one cycle
// Teylor Wong 12-02-2025

module vendingMachine (
    output logic valid,
    input logic nickel, dime, quarter,
    input logic clk, reset_n
);
    logic [6:0] total; // Using 7 bits to store cents (max 100)
    
    always_ff @(posedge clk or negedge reset_n) begin
        if (!reset_n) begin
            total <= 0;
            valid <= 0;
        end
        else begin
            // Add coin values: nickel = 5, dime = 10, quarter = 25
            total <= total + (nickel * 5) + (dime * 10) + (quarter * 25);
            
            if (total >= 100) begin
                valid <= 1;  // Assert valid for one cycle
                total <= 0;   // Reset after purchase
            end
            else begin
                valid <= 0;
            end
        end
    end
endmodule

assignment2/problem2/Simulation/vendingMachine_tb.sv
// Assignment 2: Problem2 - Vending Machine
// vendingMachine_tb.sv - testbench for vending machine
// Teylor Wong 12-02-2025

module vendingMachine_tb;
    logic valid;
    logic nickel, dime, quarter;
    logic clk, reset_n;

    vendingMachine dut (.valid(valid), .nickel(nickel), .dime(dime), .quarter(quarter), .clk(clk), .reset_n(reset_n));

    // Generate a clock signal (10ns period)
    always begin
        clk = 0; #5;
        clk = 1; #5;
    end

    initial begin
        // Initialize signals
        reset_n = 0; nickel = 0; dime = 0; quarter = 0;
        #10;
        reset_n = 1;  // Release reset
        #10;
        
        dime = 1; quarter = 1; #10; // resting multipl inputs simultaneously
        quarter = 0; dime = 0; #10;
        dime = 1; #10; dime = 0; #10;
        dime = 1; #10; dime = 0; #10;
        
        quarter = 1; #10; quarter = 0; #10;

        nickel = 1; #10; nickel = 0; #10;
        nickel = 1; #10; nickel = 0; #10;
        nickel = 1; #10; nickel = 0; #10;
        nickel = 1; #10; nickel = 0; #10;

        // valid should be asserted at this point
        #10

        $stop;
    end

    initial begin
        $dumpfile("vendingMachine_wave.vcd");
        $dumpvars(0, vendingMachine_tb);
    end
endmodule

assignment2/problem2/Simulation/vendingMachine_wave.vcd
$date
	Thu Feb 13 14:25:21 2025
$end
$version
	ModelSim Version 10.5b
$end
$timescale
	1ps
$end

$scope module vendingMachine_tb $end
$var reg 1 ! valid $end
$var reg 1 " nickel $end
$var reg 1 # dime $end
$var reg 1 $ quarter $end
$var reg 1 % clk $end
$var reg 1 & reset_n $end

$scope module dut $end
$var reg 1 ' valid $end
$var wire 1 ( nickel $end
$var wire 1 ) dime $end
$var wire 1 * quarter $end
$var wire 1 + clk $end
$var wire 1 , reset_n $end
$var reg 7 - total [6:0] $end
$upscope $end
$upscope $end
$enddefinitions $end
#0
$dumpvars
0!
0"
0#
0$
0%
0&
0'
b0 -
0(
0)
0*
0+
0,
$end
#5
1%
1+
#10
1&
0%
1,
0+
#15
1%
1+
#20
1#
1$
0%
1)
1*
0+
#25
1%
1+
b100011 -
#30
0$
0#
0%
0*
0)
0+
#35
1%
1+
#40
1#
0%
1)
0+
#45
1%
1+
b101101 -
#50
0#
0%
0)
0+
#55
1%
1+
#60
1#
0%
1)
0+
#65
1%
1+
b110111 -
#70
0#
0%
0)
0+
#75
1%
1+
#80
1$
0%
1*
0+
#85
1%
1+
b1010000 -
#90
0$
0%
0*
0+
#95
1%
1+
#100
1"
0%
1(
0+
#105
1%
1+
b1010101 -
#110
0"
0%
0(
0+
#115
1%
1+
#120
1"
0%
1(
0+
#125
1%
1+
b1011010 -
#130
0"
0%
0(
0+
#135
1%
1+
#140
1"
0%
1(
0+
#145
1%
1+
b1011111 -
#150
0"
0%
0(
0+
#155
1%
1+
#160
1"
0%
1(
0+
#165
1%
1+
b1100100 -
#170
0"
0%
0(
0+
#175
1%
1+
1'
b0 -
1!
#180
0%
0+
#185
1%
1+
0'
0!
#190
1$
1"
0%
1*
1(
0+
#195
1%
1+
b11110 -
#200
0$
0"
0%
0*
0(
0+
